annoy/__init__.py
annoy/__init__.pyi
annoy/annoylib.cpython-310-i386-linux-gnu.so
annoy/py.typed
annoy_mm-1.17.3.dist-info/METADATA
annoy_mm-1.17.3.dist-info/WHEEL
annoy_mm-1.17.3.dist-info/top_level.txt
annoy_mm-1.17.3.dist-info/RECORD
annoy_mm-1.17.3.dist-info/licenses/LICENSE
